astromcad/__init__.py
astromcad/astromcad.py
astromcad/Models/HostClassifier.h5
astromcad/Models/HostMCIF.pickle
astromcad/Models/NoHostClassifier.h5
astromcad/Models/NoHostMCIF.pickle
astromcad/Models/__init__.py
astromcad-1.2.7.dist-info/LICENSE
astromcad-1.2.7.dist-info/METADATA
astromcad-1.2.7.dist-info/WHEEL
astromcad-1.2.7.dist-info/top_level.txt
astromcad-1.2.7.dist-info/RECORD
