Metadata-Version: 2.1
Name: astromcad
Version: 1.2.7
Summary: Classifier-Based Anomaly Detection for Astronomical Transients
Author: Rithwik Gupta
Author-email: <rithwikca2020@gmail.com>
License: MIT
Classifier: Development Status :: 4 - Beta
Classifier: Intended Audience :: Science/Research
Classifier: License :: OSI Approved :: MIT License
Classifier: Programming Language :: Python :: 3
License-File: LICENSE
Requires-Dist: numpy
Requires-Dist: keras
Requires-Dist: tensorflow
Requires-Dist: scikit-learn
